{
  "$schema": "https://json.schemastore.org/tsconfig",
  "display": "NestJS",
  "extends": "./base.json",
  "compilerOptions": {
    "module": "CommonJS",
    "target": "ES6",
    "lib": ["ES2022"],
    "sourceMap": true,
    "declaration": true,
    "removeComments": true,
    "emitDecoratorMetadata": true,
    "experimentalDecorators": true,
    "allowSyntheticDefaultImports": true,
    "incremental": true,
    "skipLibCheck": true,
    "strictNullChecks": false,
    "noImplicitAny": false,
    "strictBindCallApply": false,
    "noFallthroughCasesInSwitch": false
  }
}
